xarsed/common/__init__.py
xarsed/common/common.py
xarsed/common/plotting.py
xarsed/common/statistical_process.py
xarsed/common/data/GLDAS.nc
xarsed/common/data/MERRA2.nc
xarsed/solar/__init__.py
xarsed/solar/photovoltaics.py
xarsed/solar/solar_common.py
xarsed/solar/solar_graphing.py
xarsed/solar/solar_scenario.py
xarsed/solution/__init__.py
xarsed/solution/reporting.py
xarsed/solution/solution_details.py
xarsed/solution/solution_overview.py
xarsed/solution/warning_recommendation.py
xarsed-0.0.0.dist-info/licenses/LICENSE
xarsed-0.0.0.dist-info/METADATA
xarsed-0.0.0.dist-info/WHEEL
xarsed-0.0.0.dist-info/top_level.txt
xarsed-0.0.0.dist-info/RECORD
